cdu/__init__.py
cdu/manage.py
cdu/settings.py
cdu/urls.py
cdu/wsgi.py
warrant/__init__.py
warrant/aws_srp.py
warrant/exceptions.py
warrant/django/__init__.py
warrant/django/backend.py
warrant/django/forms.py
warrant/django/middleware.py
warrant/django/models.py
warrant/django/tests.py
warrant/django/urls.py
warrant/django/utils.py
warrant/django/demo/__init__.py
warrant/django/demo/forms.py
warrant/django/demo/models.py
warrant/django/demo/urls.py
warrant/django/demo/views.py
warrant/django/migrations/__init__.py
warrant/django/views/__init__.py
warrant/django/views/profile.py
warrant/django/views/subscriptions.py
warrant/tests/__init__.py
warrant/tests/tests.py
warrant-0.6.0.dist-info/DESCRIPTION.rst
warrant-0.6.0.dist-info/METADATA
warrant-0.6.0.dist-info/RECORD
warrant-0.6.0.dist-info/WHEEL
warrant-0.6.0.dist-info/metadata.json
warrant-0.6.0.dist-info/top_level.txt
warrant-0.6.0.dist-info/zip-safe
